mojadateconverter70/__init__.py
mojadateconverter70/mojadateconverter70.py
mojadateconverter70-0.0.4.dist-info/METADATA
mojadateconverter70-0.0.4.dist-info/WHEEL
mojadateconverter70-0.0.4.dist-info/top_level.txt
mojadateconverter70-0.0.4.dist-info/RECORD
