Metadata-Version: 2.1
Name: mojadateconverter70
Version: 0.0.4
Summary: some functions related to date, with not much accuracy
Author: Mohammadali Jalili
